trashf/__init__.py
trashf/trashf.py
trashf-1.0.3.dist-info/LICENSE
trashf-1.0.3.dist-info/METADATA
trashf-1.0.3.dist-info/WHEEL
trashf-1.0.3.dist-info/entry_points.txt
trashf-1.0.3.dist-info/top_level.txt
trashf-1.0.3.dist-info/RECORD
