Metadata-Version: 2.1
Name: trashf
Version: 1.0.3
Summary: CLI tool to safely remove any file and directory by putting them in the trash
Home-page: https://github.com/yoarch/trashf
Author: yoarch
Author-email: yo.managements@gmail.com
License: UNKNOWN
Platform: UNKNOWN
Classifier: Programming Language :: Python :: 3
Classifier: License :: OSI Approved :: MIT License
Classifier: Operating System :: OS Independent
Requires-Python: >=3
